<?xml version="1.0" encoding="UTF-8"?>

<templates id="template" xml:space="preserve">
	 <t t-name="POSFirstPageWidget">
	    <div class="Main_Page" t-att-style='widget.get_widget_style()' >
		<div align="center">
	    <ol id="hexGrid" class="hexgrid_even">
	      <li class="hex">
	        <div class="hexIn">
	          <a class="hexLink hotel" href="#">
	          
	            <img  src="https://image.flaticon.com/icons/svg/227/227365.svg" alt="" />
	            <h1>HOME</h1>
	            <p><t t-esc="widget.pos.config.id"/></p>
	          </a>
	        </div>
	      </li>
	      <li class="hex">
	        <div class="hexIn">
	          <a class="hexLink reservation" href="#">
	            <img src="https://image.flaticon.com/icons/svg/227/227333.svg" alt="" />
	            <h1>RESERVATION</h1>
	            <p></p>
	          </a>
	        </div>
	      </li>
		</ol>
		<ol id="hexGrid" class="hexgrid_odd">
	      <li class="hex">
	        <div class="hexIn">
	          <a class="hexLink checkin" href="#">
	            <img src="https://image.flaticon.com/icons/svg/227/227385.svg" alt="" />
	            <h1>CHECK IN</h1>
	            <p></p>
	          </a>
	        </div>
	      </li>
	      <li class="hex">
	        <div class="hexIn">
	          <a class="night_audit hexLink" href="#">
	            <img src="/skit_pos_hm_night_audit/static/src/img/night_audit_1.png" alt="" />
	            <h1>Night Audit</h1>
	            <p></p>
	          </a>
	        </div>
	      </li>
	      <li class="hex">
	        <div class="hexIn">
	          <a class="hexLink checkout" href="#">
	            <img src="https://image.flaticon.com/icons/svg/227/227339.svg" alt="" />
	            <h1>CheckOut</h1>
	            <p></p>
	          </a>
	        </div>
	      </li>
		</ol>
		<ol id="hexGrid" class="hexgrid_even">
	      <li class="hex">
	        <div class="hexIn">
	          <a class="hexLink roomstatus" href="#">
	            <img src="https://image.flaticon.com/icons/svg/227/227302.svg" alt="" />
	            <h1>ROOM SERVICE</h1>
	            <p></p>
	          </a>
	        </div>
	      </li>
	      <li class="hex">
	        <div class="hexIn">
	          <a class="hexLink" href="#">
	            <img src="https://image.flaticon.com/icons/svg/227/227348.svg" alt="" />
	            <h1>ROOM STATUS</h1>
	            <p></p>
	          </a>
	        </div>
	      </li>
		</ol>
	</div>
	</div>
    </t>
</templates>
